rag_url_agent/__init__.py
rag_url_agent/agent.py
rag_url_agent/simple_api.py
rag_url_agent/config/__init__.py
rag_url_agent/config/settings.json
rag_url_agent/core/__init__.py
rag_url_agent/core/browser_extractor.py
rag_url_agent/core/chroma_storage.py
rag_url_agent/core/content_extractor.py
rag_url_agent/core/rag_engine.py
rag_url_agent/core/security_scanner.py
rag_url_agent/core/storage_manager.py
rag_url_agent/core/url_processor.py
rag_url_agent/integrations/__init__.py
rag_url_agent/integrations/langchain.py
rag_url_agent/integrations/llamaindex.py
rag_url_agent/integrations/llm_providers.py
rag_url_agent/integrations/llm_router.py
rag_url_agent/integrations/ollama_client.py
rag_url_agent/integrations/rag_engine.py
rag_url_agent/utils/__init__.py
rag_url_agent/utils/logger.py
rag_url_agent/utils/memory_monitor.py
rag_url_agent_sujal-1.0.4.dist-info/METADATA
rag_url_agent_sujal-1.0.4.dist-info/WHEEL
rag_url_agent_sujal-1.0.4.dist-info/top_level.txt
rag_url_agent_sujal-1.0.4.dist-info/RECORD
